Metadata-Version: 2.4
Name: artemis-mcp-fastmcp
Version: 0.1.7
Summary: Artemis MCP Server to Connect with Artemis API and Create ART Formulas
Author-email: Son Do <team@artemis.xyz>
Project-URL: Homepage, https://github.com/fastmcp-me/artemis-mcp#readme
Project-URL: Repository, https://github.com/fastmcp-me/artemis-mcp.git
Project-URL: Issues, https://github.com/fastmcp-me/artemis-mcp/issues
Keywords: artemis,mcp,crypto,stablecoins,digital finance
Requires-Python: >=3.10
Requires-Dist: build>=1.2.2.post1
Requires-Dist: httpx>=0.28.1
Requires-Dist: mcp[cli]>=1.3.0
Requires-Dist: twine>=6.1.0
